openstack_lb_info/__init__.py
openstack_lb_info/formatters.py
openstack_lb_info/loadbalancer_info.py
openstack_lb_info/main.py
openstack_lb_info/openstack_api.py
openstack_lb_info-0.2.1.dist-info/licenses/LICENSE
openstack_lb_info-0.2.1.dist-info/METADATA
openstack_lb_info-0.2.1.dist-info/WHEEL
openstack_lb_info-0.2.1.dist-info/entry_points.txt
openstack_lb_info-0.2.1.dist-info/top_level.txt
openstack_lb_info-0.2.1.dist-info/RECORD
