Metadata-Version: 2.4
Name: openstack-lb-info
Version: 0.2.1
Summary: A script to display OpenStack Load Balancer resource details.
Author: Thobias Salazar Trevisan
License: MIT License
Project-URL: Homepage, https://github.com/thobiast/openstack-loadbalancer-info
Project-URL: Source, https://github.com/thobiast/openstack-loadbalancer-info
Requires-Python: >=3.7
License-File: LICENSE
Requires-Dist: openstacksdk
Requires-Dist: rich
Dynamic: license-file
